pagtestyyb/__init__.py
pagtestyyb/print1.py
pagtestyyb/print2.py
pagtestyyb-1.0.2.dist-info/METADATA
pagtestyyb-1.0.2.dist-info/WHEEL
pagtestyyb-1.0.2.dist-info/top_level.txt
pagtestyyb-1.0.2.dist-info/RECORD
