Metadata-Version: 2.1
Name: pagtestyyb
Version: 1.0.2
Summary: A print test for PyPI
Home-page: https://www.python.org/
Author: winycg
Author-email: 1064804095@qq.com
License: MIT
Project-URL: Documentation, https://packaging.python.org/tutorials/distributing-packages/
Project-URL: Funding, https://donate.pypi.org
Project-URL: Source, https://github.com/pypa/sampleproject/
Project-URL: Tracker, https://github.com/pypa/sampleproject/issues
Keywords: ga nn
Platform: UNKNOWN
Requires-Python: >=3
Requires-Dist: numpy (>=1.14)
